thesaurus.py
thesaurus_cli-1.0.1.dist-info/METADATA
thesaurus_cli-1.0.1.dist-info/RECORD
thesaurus_cli-1.0.1.dist-info/WHEEL
thesaurus_cli-1.0.1.dist-info/entry_points.txt
thesaurus_cli-1.0.1.dist-info/top_level.txt
