Metadata-Version: 2.1
Name: thesaurus-cli
Version: 1.0.1
Summary: A command line interface for Thesaurus.com
Home-page: https://github.com/davidgu/thesaurus-cli
Author: David Gu
Author-email: UNKNOWN
License: UNKNOWN
Platform: UNKNOWN
Requires-Dist: beautifulsoup4
